medical_shape/__init__.py
medical_shape/apply_to_collection.py
medical_shape/normalization.py
medical_shape/shape.py
medical_shape/subject.py
medical_shape/io/__init__.py
medical_shape/io/read.py
medical_shape/io/write.py
medical_shape/transforms/__init__.py
medical_shape/transforms/copy_affine.py
medical_shape/transforms/mixin.py
medical_shape/transforms/resample.py
medical_shape/transforms/to_canonical.py
medical_shape/transforms/to_orientation.py
scripts/shape_to_canonical.py
tests/transforms/__init__.py
tests/transforms/test_to_orientation.py
medical_shape-0.1.2.dist-info/METADATA
medical_shape-0.1.2.dist-info/WHEEL
medical_shape-0.1.2.dist-info/top_level.txt
medical_shape-0.1.2.dist-info/zip-safe
medical_shape-0.1.2.dist-info/RECORD
