Metadata-Version: 2.1
Name: medical-shape
Version: 0.1.2
Summary: A torchio extension for shape processing
Author: Justus Schock
Author-email: justus.schock@posteo.de
Maintainer-email: Justus Schock <justus.schock@posteo.de>
Project-URL: Homepage, https://github.com/justusschock/medical-shape
Project-URL: Repository, https://github.com/justusschock/medical-shape
Project-URL: Bug Reports, https://github.com/justusschock/medical-shape/issues
Keywords: deep learning,machine learning,pytorch,medical,healthcare,AI
Classifier: Programming Language :: Python :: 3
Requires-Python: >=3.7
Requires-Dist: torch (>=1.7.*)
Requires-Dist: rising (>=0.2.1)
Requires-Dist: torchio (>=0.18.71)
